__init__.py
backend_shim.py
ol_openedx_logging/__init__.py
ol_openedx_logging/app.py
ol_openedx_logging/settings/__init__.py
ol_openedx_logging/settings/production.py
ol_openedx_logging-0.2.0.dist-info/METADATA
ol_openedx_logging-0.2.0.dist-info/WHEEL
ol_openedx_logging-0.2.0.dist-info/entry_points.txt
ol_openedx_logging-0.2.0.dist-info/namespace_packages.txt
ol_openedx_logging-0.2.0.dist-info/top_level.txt
ol_openedx_logging-0.2.0.dist-info/RECORD
