Metadata-Version: 2.1
Name: ol-openedx-logging
Version: 0.2.0
Summary: An Open edX plugin to customize the logging configuration used by the edx-platform application
License: BSD-3-Clause
Requires-Python: >=3.8
Requires-Dist: Django (>2.0)
Requires-Dist: python-json-logger (<3.0.0,>=2.0.2)
